README.rst
setup.cfg
setup.py
hermes/__init__.py
hermes/analysis.py
hermes/examples.py
hermes/geometry.py
hermes/main.py
hermes/objects.py
hermes/orientation.py
hermes/propagation_bulk.py
hermes/simulation.py
hermes/util.py
hermes/constellations/O3b_constellation.py
hermes/constellations/__init__.py
hermes_simulator.egg-info/PKG-INFO
hermes_simulator.egg-info/SOURCES.txt
hermes_simulator.egg-info/dependency_links.txt
hermes_simulator.egg-info/requires.txt
hermes_simulator.egg-info/top_level.txt