Metadata-Version: 1.1
Name: hermes-simulator
Version: 0.1.3b0
Summary: Simulator for satellite data relay systems
Home-page: https://github.com/Josvth/hermes-simulator
Author: Jos van 't Hof
Author-email: josvth@gmail.com
License: GPL3+
Download-URL: https://github.com/Josvth/hermes-simulator/archive/v0.1.2beta.tar.gz
Keywords: data,relay,satellite
Platform: UNKNOWN
Classifier: Development Status :: 3 - Alpha
Classifier: Intended Audience :: Developers
Classifier: Topic :: Software Development :: Build Tools
Classifier: License :: OSI Approved :: GNU General Public License v3 or later (GPLv3+)
Classifier: Programming Language :: Python :: 3
Classifier: Programming Language :: Python :: 3.4
Classifier: Programming Language :: Python :: 3.5
Classifier: Programming Language :: Python :: 3.6
